airun/__init__.py
airun/client.py
airun/exceptions.py
airun/http_client.py
airun/models.py
airun/resources/chat.py
airun/resources/code.py
airun/resources/rag.py
airun/resources/report.py
airun/resources/sessions.py
airun/resources/user.py
airun/resources/web.py
airun_sdk-1.0.6.dist-info/METADATA
airun_sdk-1.0.6.dist-info/WHEEL
airun_sdk-1.0.6.dist-info/top_level.txt
airun_sdk-1.0.6.dist-info/RECORD
