Metadata-Version: 2.4
Name: airun-sdk
Version: 1.0.6
Summary: Python SDK for Hamonize AIRUN API
Author-email: Hamonize Team <team@hamonize.kr>
License: MIT
Project-URL: Homepage, https://github.com/hamonikr/airun
Project-URL: Documentation, https://docs.hamonize.kr/airun
Project-URL: Repository, https://github.com/hamonikr/airun.git
Project-URL: Bug Tracker, https://github.com/hamonikr/airun/issues
Keywords: hamonize,airun,api,sdk,ai,rag
Classifier: Development Status :: 5 - Production/Stable
Classifier: Intended Audience :: Developers
Classifier: License :: OSI Approved :: MIT License
Classifier: Programming Language :: Python :: 3
Classifier: Programming Language :: Python :: 3.8
Classifier: Programming Language :: Python :: 3.9
Classifier: Programming Language :: Python :: 3.10
Classifier: Programming Language :: Python :: 3.11
Classifier: Programming Language :: Python :: 3.12
Classifier: Topic :: Software Development :: Libraries :: Python Modules
Classifier: Topic :: Scientific/Engineering :: Artificial Intelligence
Requires-Python: >=3.8
Requires-Dist: requests>=2.28.0
Requires-Dist: python-dotenv>=1.0.0
Requires-Dist: pydantic>=2.0.0
Requires-Dist: typing-extensions>=4.5.0
Requires-Dist: websocket-client>=1.6.0
Requires-Dist: websockets>=12.0
Provides-Extra: dev
Requires-Dist: pytest>=7.0.0; extra == "dev"
Requires-Dist: pytest-asyncio>=0.21.0; extra == "dev"
Requires-Dist: black>=23.0.0; extra == "dev"
Requires-Dist: isort>=5.12.0; extra == "dev"
Requires-Dist: mypy>=1.0.0; extra == "dev"
Requires-Dist: flake8>=6.0.0; extra == "dev"
